getAddressAndCMD.v
module getCMD(frame,AD,CBE,CMD);
// ##### Declaration #####
input wire frame;
input wire[31:0] AD;
input wire[3:0] CBE;
output reg[3:0] CMD;

// ##### process #####
always@(negedge frame) begin 
CMD <= CBE;
end

endmodule

buffer.v
module buffer(clk,frame,CBE,AD,IRDY,TRDY);
// ##### Declaration #####
input clk;
input wire frame;
input wire[3:0] CBE;
inout wire[31:0] AD;
input wire IRDY;
output reg TRDY;

// ##### Define The Operation #####
parameter 
READ = 4'b0110,
WRITE = 4'b0111;

//Counters
reg[2:0] readCount = 0,writeCount =0;
reg[9:0] memCount=0;

reg[31:0] BUFFER[0:3]; //Buffer in the slave
reg[31:0] memory[0:1023]; //Internal Memory for storage;
wire[3:0] operation; //incoming operation from CBE "Command"


// ##### process #####
getCMD get1(.frame(frame),.AD(AD),.CBE(CBE),.CMD(operation)); //get Command and put it in operation

// Tracking writeCount to rise TRDY ((( BUSY )))
always@(negedge clk) begin 

if(writeCount==4) begin 
 TRDY = 1;
end
if(writeCount==0)begin TRDY=0; end


end

// Transfer Data from buffer when it is fill  ((( TRANSFERING )))
always@(posedge clk) begin 

if(TRDY==1 && writeCount==4) begin
memory[memCount] <= BUFFER[0];
memory[memCount+1] <= BUFFER[1];
memory[memCount+2] <= BUFFER[2];
memory[memCount+3] <= BUFFER[3];
memCount <= memCount + 4;
writeCount = 0;
end

end


// Tracking IRDY To making operations
always@(posedge clk) begin 

// Check IRDY To do a Operation
if(IRDY == 0 && TRDY == 0) begin 
// Make the operation
case(operation)
READ: begin
readCount=readCount+1;
readCount=(readCount==4)? 0:readCount;
end 

WRITE: begin 
BUFFER[writeCount] = AD;
writeCount=writeCount+1;
end
 
default: ; //Feh default hnaaa 

endcase

end

end

// At Reading ONLY
assign AD = (operation==READ)? BUFFER[readCount]:32'bZ ;


endmodule

clock.v
module clockGen (clk);
output clk;
reg clk;

initial
clk=0;

always 
#5 clk=~clk;

endmodule

t_buffer.v
`timescale 1ns/1ns
`include "clock.v"
`include "buffer.v"
`include "getAddressAndCMD.v"
module buffertestbench;
reg tframe;
reg[3:0] tCBE;
reg tIRDY;
reg [31:0] tAD;
reg operation;

wire [31:0] in_out;
wire tTRDY;



parameter READ = 1;
parameter WRITE = 0;

assign in_out = (operation == WRITE) ? tAD : 32'bZ;


initial 
begin
    $dumpfile("t_buffer.vcd");
    $dumpvars(0, buffertestbench);

tframe = 1;
tIRDY = 1;

#10 
tframe = 0;
tIRDY = 0;
tCBE = 4'b0111;
operation = WRITE;


tAD = 32'd287;
#10

tAD = 32'd1000;
#10

tAD = 32'd133;
#10

tAD = 32'd176;
#10

tAD = 32'haa;
#20

tAD = 32'hbb;
#10

tAD = 32'hcc;
#10

tAD = 32'hdd;
#10

tAD = 32'hee;
#20

tframe = 1;
tIRDY = 1;


#10
tframe = 0;
tIRDY = 0;
tCBE = 4'b0110;
operation = READ;


$finish;
end



clockGen c1(clk);
buffer B1(clk, tframe, tCBE, in_out, tIRDY, tTRDY);



endmodule

t_buffer.vcd
$date
	Tue Dec 22 23:42:46 2020
$end
$version
	Icarus Verilog
$end
$timescale
	1ns
$end
$scope module buffertestbench $end
$var wire 32 ! in_out [31:0] $end
$var wire 1 " tTRDY $end
$var wire 1 # clk $end
$var reg 1 $ operation $end
$var reg 32 % tAD [31:0] $end
$var reg 4 & tCBE [3:0] $end
$var reg 1 ' tIRDY $end
$var reg 1 ( tframe $end
$scope module B1 $end
$var wire 32 ) AD [31:0] $end
$var wire 4 * CBE [3:0] $end
$var wire 1 ' IRDY $end
$var wire 1 ( frame $end
$var wire 4 + operation [3:0] $end
$var wire 1 # clk $end
$var reg 1 " TRDY $end
$var reg 10 , memCount [9:0] $end
$var reg 3 - readCount [2:0] $end
$var reg 3 . writeCount [2:0] $end
$scope module get1 $end
$var wire 32 / AD [31:0] $end
$var wire 4 0 CBE [3:0] $end
$var wire 1 ( frame $end
$var reg 4 1 CMD [3:0] $end
$upscope $end
$upscope $end
$scope module c1 $end
$var reg 1 # clk $end
$upscope $end
$upscope $end
$enddefinitions $end
#0
$dumpvars
bx 1
bx 0
bx /
b0 .
b0 -
b0 ,
bx +
bx *
bx )
1(
1'
bx &
bx %
x$
0#
x"
bx !
$end
#5
1#
#10
b100011111 !
b100011111 )
b100011111 /
b111 +
b111 1
0"
0#
b100011111 %
0$
b111 &
b111 *
b111 0
0'
0(
#15
b1 .
1#
#20
b1111101000 !
b1111101000 )
b1111101000 /
0#
b1111101000 %
#25
b10 .
1#
#30
b10000101 !
b10000101 )
b10000101 /
0#
b10000101 %
#35
b11 .
1#
#40
b10110000 !
b10110000 )
b10110000 /
0#
b10110000 %
#45
b100 .
1#
#50
1"
b10101010 !
b10101010 )
b10101010 /
0#
b10101010 %
#55
b100 ,
b0 .
1#
#60
0"
0#
#65
b1 .
1#
#70
b10111011 !
b10111011 )
b10111011 /
0#
b10111011 %
#75
b10 .
1#
#80
b11001100 !
b11001100 )
b11001100 /
0#
b11001100 %
#85
b11 .
1#
#90
b11011101 !
b11011101 )
b11011101 /
0#
b11011101 %
#95
b100 .
1#
#100
1"
b11101110 !
b11101110 )
b11101110 /
0#
b11101110 %
#105
b1000 ,
b0 .
1#
#110
0"
0#
#115
b1 .
1#
#120
0#
1'
1(
#125
1#
#130
b110 +
b110 1
b11101110 !
b11101110 )
b11101110 /
0#
1$
b110 &
b110 *
b110 0
0'
0(
