verifyAddress.v
module verifyAddress(clk,frame,AD,DEVSEL,TRDY);

//##### Decleration #####
parameter deviceAddress = 1000; //Specific address for a device

input wire clk;
input wire frame;
input wire[31:0] AD;
output reg DEVSEL;
output reg TRDY;
reg [2:0] counter=0;
reg [2:0] elCounterElTany=0;
reg[31:0] recievedAddress;


//##### Process #####

always@(negedge clk)begin

if(frame==1)begin 
if(elCounterElTany<=3)begin 
elCounterElTany=elCounterElTany+1;
end


if(elCounterElTany==3)begin
DEVSEL = 1 ; //Active LOW
TRDY = 1; //Active LOW
counter=0;
end

end

end

always@(AD)begin 
if(counter==1)begin
recievedAddress=AD;
end

end


always@(negedge clk) begin 
if(frame==0)begin
 
/*if(counter==0)begin 
recievedAddress=AD;
end*/

if(counter<=3)begin 
counter=counter+1;
end


if(counter==3) begin
DEVSEL = (recievedAddress==deviceAddress)? 0:1 ; //Active LOW
TRDY = (recievedAddress==deviceAddress)? 0:1 ; //Active LOW


end

end


end


endmodule

getAddressAndCMD.v
module getCMD(frame,CBE,CMD);
// ##### Declaration #####
input wire frame;
input wire[3:0] CBE;
output reg[3:0] CMD;

// ##### process #####
always@(negedge frame) begin 
CMD = CBE;
end

endmodule

buffer.v
module buffer(clk,frame,CBE,AD,IRDY,TRDY,DEVSEL);
// ##### Declaration #####
input clk;
input wire frame;
input wire[3:0] CBE;
inout wire[31:0] AD;
input wire IRDY;
output reg TRDY;
output DEVSEL;

// ##### Define The Operation #####
parameter 
READ = 4'b0110,
WRITE = 4'b0111;

//Counters
reg[2:0] readCount = -1,writeCount =0;
reg[9:0] memCount=0;

reg[31:0] BUFFER[0:3]; //Buffer in the slave
reg[31:0] memory[0:1023]; //Internal Memory for storage;
wire[3:0] operation; //incoming operation from CBE "Command"



// ##### process #####
getCMD get1(frame,CBE,operation);
wire hhh;
verifyAddress verify1(.clk(clk),.frame(frame),.AD(AD),.DEVSEL(DEVSEL),.TRDY(hhh));

always@(hhh)begin
TRDY=hhh;
end

// Tracking writeCount to rise TRDY ((( BUZY )))
always@(negedge clk) begin 

if(writeCount==4) begin 
 TRDY = 1; 
end
if(writeCount==0&&TRDY==1&&DEVSEL==0)begin TRDY=0; end


end

// Transfer Data from buffer when it is fill  ((( TRANSFERING )))
always@(posedge clk) begin 

if(TRDY==1&&writeCount==4) begin 
memory[memCount]<=BUFFER[0];
memory[memCount+1]<=BUFFER[1];
memory[memCount+2]<=BUFFER[2];
memory[memCount+3]<=BUFFER[3];
memCount<=memCount+4;
writeCount=0;
//TRDY=0;
end

end


// Tracking IRDY To making operations
always@(posedge clk) begin 

// Check IRDY To do a Operation
if(IRDY==0&&TRDY==0) begin 
// Make the operation
case(operation)
READ: begin
readCount=readCount+1;
readCount=(readCount==4)? 0:readCount;
end 

WRITE: begin 
BUFFER[writeCount] = {AD[31:24]&{8{CBE[3]}},AD[23:16]&{8{CBE[2]}},AD[15:8]&{8{CBE[1]}},AD[7:0]&{8{CBE[0]}}};
writeCount=writeCount+1;
end
 
default: begin
readCount=readCount+1;
readCount=(readCount==4)? 0:readCount;
end

endcase

end

end

// At Reading ONLY
assign AD = (operation==READ&&TRDY==0&&DEVSEL==0)? BUFFER[readCount]:32'bZ ;




endmodule

clock.v
module clockGen (clk);
output clk;
reg clk;

initial
clk=0;

always 
#5 clk=~clk;

endmodule

testcase1.v
`timescale 1ns/1ns
`include "clock.v"
`include "verifyAddress.v"
`include "getAddressAndCMD.v"
`include "buffer.v"


module t_buffertest;
reg tframe;
reg[3:0] tCBE;
reg tIRDY;
reg [31:0] tAD;
reg[3:0] operation;

wire [31:0] in_out;
wire tTRDY;
wire tDEVSEL;

parameter READ = 4'b0110;
parameter WRITE = 4'b0111;


//getCMD get2(tframe,tCBE,operation);
assign in_out = (operation==WRITE)? tAD:32'bZ;


initial 
begin
$dumpfile("testcase1.vcd");
$dumpvars(0, t_buffertest);


tframe = 1;
tIRDY = 1;
#10 


// Frame Start
tframe = 0;


operation=WRITE;
tCBE = 4'b0111;
tAD = 32'd1000;
#10
tIRDY=0;
#10                


// Operation Write
tCBE = 4'b0101;
tAD = 32'haaaaaaaa;
#10



// Operation Write
tCBE = 4'b1111;
tAD = 32'hbbbbbbbb;
#10



// Operation Write
tCBE = 4'b0101;
tAD = 32'haaaacccc;
#10



// Operation Write
tCBE = 4'b1100;
tAD = 32'hdddddddd;
#10



// Frame End
tframe = 1;
#10 
tIRDY = 1;
#10 
    


// Frame Start
tframe = 0;


// Operation Read
tCBE = 4'b0110;
tAD = 32'd1000;
#10
tIRDY = 0;
operation=READ;
#80


// Frame End
tframe = 1;
#10 
tIRDY = 1;
#10 
    




// tframe = 1;
// tIRDY = 1;

// #10 
// operation=WRITE;
// tframe = 0;

// tCBE = 4'b0111;
// tAD = 32'd1000;

// #10
// tIRDY=0;
// #10


// tCBE=4'b0101;
// tAD=32'hffffffff;
// #10

// tAD=32'd133;
// #10

// tCBE=4'b1111;
// tAD=32'd176;
// #10

// tAD=32'haa;
// #30

// tAD=32'hbb;
// #10

// tAD=32'hcc;
// #10

// tAD=32'hdd;
// #10

// tframe = 1;
// #10
// tIRDY = 1;
// #10

// tframe = 0;
// tCBE = 4'b0110;
// tAD = 32'd1000;
// #10
// tIRDY = 0;
// operation=READ;

$finish;
end



clockGen c1(clk);
buffer B1(clk,tframe,tCBE,in_out,tIRDY,tTRDY,tDEVSEL);



endmodule

testcase1.vcd
$date
	Wed Dec 23 14:17:24 2020
$end
$version
	Icarus Verilog
$end
$timescale
	1ns
$end
$scope module t_buffertest $end
$var wire 32 ! in_out [31:0] $end
$var wire 1 " tTRDY $end
$var wire 1 # tDEVSEL $end
$var wire 1 $ clk $end
$var reg 4 % operation [3:0] $end
$var reg 32 & tAD [31:0] $end
$var reg 4 ' tCBE [3:0] $end
$var reg 1 ( tIRDY $end
$var reg 1 ) tframe $end
$scope module B1 $end
$var wire 32 * AD [31:0] $end
$var wire 4 + CBE [3:0] $end
$var wire 1 ( IRDY $end
$var wire 1 ) frame $end
$var wire 4 , operation [3:0] $end
$var wire 1 - hhh $end
$var wire 1 $ clk $end
$var wire 1 # DEVSEL $end
$var reg 1 " TRDY $end
$var reg 10 . memCount [9:0] $end
$var reg 3 / readCount [2:0] $end
$var reg 3 0 writeCount [2:0] $end
$scope module get1 $end
$var wire 4 1 CBE [3:0] $end
$var wire 1 ) frame $end
$var reg 4 2 CMD [3:0] $end
$upscope $end
$scope module verify1 $end
$var wire 32 3 AD [31:0] $end
$var wire 1 ) frame $end
$var wire 1 $ clk $end
$var reg 1 # DEVSEL $end
$var reg 1 - TRDY $end
$var reg 3 4 counter [2:0] $end
$var reg 3 5 elCounterElTany [2:0] $end
$var reg 32 6 recievedAddress [31:0] $end
$upscope $end
$upscope $end
$scope module c1 $end
$var reg 1 $ clk $end
$upscope $end
$upscope $end
$enddefinitions $end
#0
$dumpvars
bx 6
b0 5
b0 4
bx 3
bx 2
bx 1
b0 0
b111 /
b0 .
x-
bx ,
bx +
bx *
1)
1(
bx '
bx &
bx %
0$
x#
x"
bx !
$end
#5
1$
#10
b1111101000 6
b1111101000 !
b1111101000 *
b1111101000 3
b1 4
b111 ,
b111 2
0$
b1111101000 &
b111 '
b111 +
b111 1
b111 %
0)
#15
1$
#20
b10 4
0$
0(
#25
1$
#30
0"
0-
0#
b11 4
b10101010101010101010101010101010 !
b10101010101010101010101010101010 *
b10101010101010101010101010101010 3
0$
b10101010101010101010101010101010 &
b101 '
b101 +
b101 1
#35
b1 0
1$
#40
b100 4
b10111011101110111011101110111011 !
b10111011101110111011101110111011 *
b10111011101110111011101110111011 3
0$
b10111011101110111011101110111011 &
b1111 '
b1111 +
b1111 1
#45
b10 0
1$
#50
b10101010101010101100110011001100 !
b10101010101010101100110011001100 *
b10101010101010101100110011001100 3
0$
b10101010101010101100110011001100 &
b101 '
b101 +
b101 1
#55
b11 0
1$
#60
b11011101110111011101110111011101 !
b11011101110111011101110111011101 *
b11011101110111011101110111011101 3
0$
b11011101110111011101110111011101 &
b1100 '
b1100 +
b1100 1
#65
b100 0
1$
#70
b1 5
1"
0$
1)
#75
b100 .
b0 0
1$
#80
0"
b10 5
0$
1(
#85
1$
#90
bx !
bx *
bx 3
b110 ,
b110 2
0$
b1111101000 &
b110 '
b110 +
b110 1
0)
#95
1$
#100
0$
b110 %
0(
#105
b101010100000000010101010 !
b101010100000000010101010 *
b101010100000000010101010 3
b0 /
1$
#110
0$
#115
b10111011101110111011101110111011 !
b10111011101110111011101110111011 *
b10111011101110111011101110111011 3
b1 /
1$
#120
0$
#125
b101010100000000011001100 !
b101010100000000011001100 *
b101010100000000011001100 3
b10 /
1$
#130
0$
#135
b11011101110111010000000000000000 !
b11011101110111010000000000000000 *
b11011101110111010000000000000000 3
b11 /
1$
#140
0$
#145
b101010100000000010101010 !
b101010100000000010101010 *
b101010100000000010101010 3
b0 /
1$
#150
0$
#155
b10111011101110111011101110111011 !
b10111011101110111011101110111011 *
b10111011101110111011101110111011 3
b1 /
1$
#160
0$
#165
b101010100000000011001100 !
b101010100000000011001100 *
b101010100000000011001100 3
b10 /
1$
#170
0$
#175
b11011101110111010000000000000000 !
b11011101110111010000000000000000 *
b11011101110111010000000000000000 3
b11 /
1$
#180
bz !
bz *
bz 3
1"
b0 4
1-
1#
b11 5
0$
1)
#185
1$
#190
b100 5
0$
1(
